{
    "A": "GENERAL WORKS",
    "AC": "Collections.  Series.  Collected works",
    "AE": "Encyclopedias",
    "AG": "Dictionaries and other general reference works",
    "AI": "Indexes",
    "AM": "Museums.  Collectors and collecting",
    "AN": "Newspapers",
    "AP": "Periodicals",
    "AS": "Academies and learned societies",
    "AY": "Yearbooks.  Almanacs.  Directories",
    "AZ": "History of scholarship and learning.  The humanities",
    "B": "PHILOSOPHY.  PSYCHOLOGY.  RELIGION",
    "BC": "Logic",
    "BD": "Speculative philosophy",
    "BF": "Psychology",
    "BH": "Aesthetics",
    "BJ": "Ethics",
    "BL": "Religions.  Mythology.  Rationalism",
    "BM": "Judaism",
    "BP": "Islam.  Bahai Faith.  Theosophy, etc.",
    "BQ": "Buddhism",
    "BR": "Christianity",
    "BS": "The Bible",
    "BT": "Doctrinal Theology",
    "BV": "Practical Theology",
    "BX": "Christian Denominations",
    "C": "AUXILIARY SCIENCES OF HISTORY",
    "CB": "History of Civilization",
    "CC": "Archaeology",
    "CD": "Diplomatics.  Archives.  Seals",
    "CE": "Technical Chronology.  Calendar",
    "CJ": "Numismatics",
    "CN": "Inscriptions.  Epigraphy",
    "CR": "Heraldry",
    "CS": "Genealogy",
    "CT": "Biography",
    "D": "WORLD HISTORY AND HISTORY OF EUROPE, ASIA, AFRICA, AUSTRALIA, NEW ZEALAND, ETC.",
    "DA": "History of Great Britain",
    "DAW": "History of Central Europe",
    "DB": "History of Austria.  Liechtenstein.  Hungary.  Czechoslovakia",
    "DC": "History of France",
    "DD": "History of Germany",
    "DE": "History of the Greco-Roman world",
    "DF": "History of Greece",
    "DG": "History of Italy",
    "DH": "History of Low Countries.  Benelux Countries",
    "DJ": "History of Netherlands (Holland)",
    "DJK": "History of Eastern Europe (General)",
    "DK": "History of Russia.  Soviet Union.  Former Soviet Republics",
    "DL": "History of Northern Europe.  Scandinavia",
    "DP": "History of Spain",
    "DQ": "History of Switzerland",
    "DR": "History of Balkan Peninsula",
    "DS": "History of Asia",
    "DT": "History of Africa",
    "DU": "History of Oceania (South Seas)",
    "DX": "History of Gypsies",
    "E": "HISTORY OF THE AMERICAS",
    "F": "HISTORY OF THE AMERICAS",
    "G": "GEOGRAPHY.  ANTHROPOLOGY.  RECREATION",
    "GA": "Mathematical geography.  Cartography",
    "GB": "Physical geography",
    "GC": "Oceanography",
    "GE": "Environmental sciences",
    "GF": "Human ecology.  Anthropogeography",
    "GN": "Anthropology",
    "GR": "Folklore",
    "GT": "Manners and customs (General)",
    "GV": "Recreation.  Leisure",
    "H": "SOCIAL SCIENCES",
    "HA": "Statistics",
    "HB": "Economic theory.  Demography",
    "HC": "Economic history and conditions",
    "HD": "Industries.  Land use.  Labor",
    "HE": "Transportation and communications",
    "HF": "Commerce",
    "HG": "Finance",
    "HJ": "Public finance",
    "HM": "Sociology (General)",
    "HN": "Social history and conditions.  Social problems.",
    "HQ": "The Family.  Marriage.  Women",
    "HS": "Societies: secret, benevolent, etc.",
    "HT": "Communities.  Classes.  Races",
    "HV": "Social pathology.  Social and public welfare.",
    "HX": "Socialism.  Communism.  Anarchism",
    "J": "POLITICAL SCIENCE",
    "JA": "Political science (General)",
    "JC": "Political theory.  The state.  Theories of the state",
    "JF": "Political institutions and public administration",
    "JJ": "Political institutions and public administration",
    "JK": "Political institutions and public administration",
    "JL": "Political institutions and public administration",
    "JN": "Political institutions and public administration (Europe)",
    "JQ": "Political institutions and public administration (Asia,",
    "JS": "Local government.  Municipal government",
    "JV": "Colonies and colonization.  Emigration and",
    "JX": "International law, see JZ and KZ",
    "JZ": "International relations",
    "K": "LAW",
    "KB": "Religious law in general.  Comparative religious law.",
    "KBM": "Jewish law.  Halakah",
    "KBP": "Islamic law.  Shar\\u012bah.  Fiqh",
    "KBR": "History of canon law",
    "KBU": "Law of the Roman Catholic Church. The Holy See",
    "KD": "Law of the United Kingdom and Ireland",
    "KDZ": "America.  North America",
    "KE": "Law of Canada",
    "KF": "Law of the United States",
    "KG": "Latin America (General)",
    "KH": "South America (General)",
    "KJ": "Europe",
    "KZ": "Law of nations",
    "L": "EDUCATION",
    "LA": "History of education",
    "LB": "Theory and practice of education",
    "LC": "Special aspects of education",
    "LD": "Individual institutions",
    "LE": "Individual institutions",
    "LF": "Individual institutions",
    "LG": "Individual institutions",
    "LH": "College and school magazines and papers",
    "LJ": "Student fraternities and societies, United States",
    "LT": "Textbooks",
    "M": "MUSIC",
    "ML": "Literature on music",
    "MT": "Instruction and study",
    "N": "FINE ARTS",
    "NA": "Architecture",
    "NB": "Sculpture",
    "NC": "Drawing.  Design.  Illustration",
    "ND": "Painting",
    "NE": "Print media",
    "NK": "Decorative arts",
    "NX": "Arts in general",
    "P": "LANGUAGE AND LITERATURE",
    "PA": "Classical philology",
    "PB": "Modern languages.  Celtic languages",
    "PC": "Romance",
    "PD": "Germanic",
    "PE": "English",
    "PF": "West Germanic",
    "PG": "Slavic.  Baltic.  Albanian",
    "PH": "Uralic.  Basque",
    "PJ": "Oriental philology and literature",
    "PK": "Indo-Iranian philology and literature",
    "PL": "Languages of Eastern Asia, Africa, Oceania",
    "PM": "Hyperborean, Indian, and artificial languages",
    "PN": "Literature (General)",
    "PQ": "French literature",
    "PR": "English literature",
    "PS": "American literature",
    "PT": "German literature",
    "PZ": "Fiction and juvenile belles lettres",
    "Q": "SCIENCE",
    "QA": "Mathematics",
    "QB": "Astronomy",
    "QC": "Physics",
    "QD": "Chemistry",
    "QE": "Geology",
    "QH": "Natural history (General)",
    "QK": "Botany",
    "QL": "Zoology",
    "QM": "Human anatomy",
    "QP": "Physiology",
    "QR": "Microbiology",
    "R": "MEDICINE",
    "RA": "Public aspects of medicine",
    "RB": "Pathology",
    "RC": "Internal medicine",
    "RD": "Surgery",
    "RE": "Ophthalmology",
    "RF": "Otorhinolaryngology",
    "RG": "Gynecology and obstetrics",
    "RJ": "Pediatrics",
    "RK": "Dentistry",
    "RL": "Dermatology",
    "RM": "Therapeutics.  Pharmacology",
    "RS": "Pharmacy and materia medica",
    "RT": "Nursing",
    "RV": "Botanic, Thomsonian, and eclectic medicine",
    "RX": "Homeopathy",
    "RZ": "Other systems of medicine",
    "S": "AGRICULTURE",
    "SB": "Plant culture",
    "SD": "Forestry",
    "SF": "Animal culture",
    "SH": "Aquaculture.  Fisheries.  Angling",
    "SK": "Hunting sports",
    "T": "TECHNOLOGY",
    "TA": "Engineering (General).  Civil engineering (General)",
    "TC": "Hydraulic engineering",
    "TD": "Environmental technology.  Sanitary engineering",
    "TE": "Highway engineering.  Roads and pavements",
    "TF": "Railroad engineering and operation",
    "TG": "Bridge engineering",
    "TH": "Building construction",
    "TJ": "Mechanical engineering and machinery",
    "TK": "Electrical engineering.  Electronics.  Nuclear engineering",
    "TL": "Motor vehicles.  Aeronautics.  Astronautics",
    "TN": "Mining engineering.  Metallurgy",
    "TP": "Chemical technology",
    "TR": "Photography",
    "TS": "Manufactures",
    "TT": "Handicrafts.  Arts and crafts",
    "TX": "Home economics",
    "U": "MILITARY SCIENCE",
    "UA": " Armies: Organization, distribution, military situation",
    "UB": "Military administration",
    "UC": "Maintenance and transportation",
    "UD": "Infantry",
    "UE": "Cavalry.  Armor",
    "UF": "Artillery",
    "UG": "Military engineering",
    "UH": "Other services",
    "V": "NAVAL SCIENCE",
    "VA": "Navies: Organization, distribution, naval situation",
    "VB": "Naval administration",
    "VC": "Naval maintenance",
    "VD": "Naval seamen",
    "VE": "Marines",
    "VF": "Naval ordnance",
    "VG": "Minor services of navies",
    "VK": "Navigation.  Merchant marine",
    "VM": "Naval architecture.  Shipbuilding.  Marine engineering",
    "Z": "BIBLIOGRAPHY.  LIBRARY SCIENCE.",
    "ZA": "Information resources (General)"
}
